setup.py
libname/__init__.py
libname/main.py
wengtimIsNotGay.egg-info/PKG-INFO
wengtimIsNotGay.egg-info/SOURCES.txt
wengtimIsNotGay.egg-info/dependency_links.txt
wengtimIsNotGay.egg-info/top_level.txt